examples/__init__.py
examples/speech_command/__init__.py
examples/speech_command/model.py
examples/speech_command/torch_al.py
examples/speech_command/util/__init__.py
examples/speech_command/util/data_loader.py
examples/speech_command/util/stft.py
tests/__init__.py
tests/test_base_query.py
tests/test_cluster.py
tests/test_data_pool.py
tests/test_data_type.py
tests/test_data_util.py
zeef/__init__.py
zeef/version.py
zeef/cl/__init__.py
zeef/cl/pipeline.py
zeef/data/__init__.py
zeef/data/base.py
zeef/data/channel.py
zeef/data/pool.py
zeef/learner/__init__.py
zeef/learner/base.py
zeef/learner/sklearn.py
zeef/learner/torch.py
zeef/strategy/__init__.py
zeef/strategy/adversarial.py
zeef/strategy/base.py
zeef/strategy/cluster.py
zeef/strategy/diversity.py
zeef/strategy/random.py
zeef/strategy/uncertainty.py
zeef/util/__init__.py
zeef/util/data_util.py
zeef/util/file_util.py
zeef-0.1.3.dist-info/LICENSE
zeef-0.1.3.dist-info/METADATA
zeef-0.1.3.dist-info/WHEEL
zeef-0.1.3.dist-info/top_level.txt
zeef-0.1.3.dist-info/RECORD
