Metadata-Version: 2.1
Name: zeef
Version: 0.1.3
Summary: A Python Framework for Deep Active Learning
Home-page: https://github.com/MLSysOps/zeef
Author: Yizheng Huang
Author-email: huangyz0918@gmail.com
License: UNKNOWN
Download-URL: https://github.com/MLSysOps/zeef/archive/master.zip
Keywords: active learning,deep learning,data processing,data mining,neural networks
Platform: UNKNOWN
Classifier: Development Status :: 5 - Production/Stable
Classifier: Intended Audience :: Education
Classifier: Intended Audience :: Financial and Insurance Industry
Classifier: Intended Audience :: Science/Research
Classifier: Intended Audience :: Developers
Classifier: Intended Audience :: Information Technology
Classifier: License :: OSI Approved :: Apache Software License
Classifier: Programming Language :: Python :: 3
Classifier: Operating System :: OS Independent
License-File: LICENSE
Requires-Dist: numpy (>=1.13)
Requires-Dist: scikit-learn (>=0.20.0)
Requires-Dist: setuptools (==58.0.4)
Requires-Dist: tqdm (==4.62.3)
